LICENSE
MANIFEST.in
README.rst
setup.py
il2fb/config/difficulty/__init__.py
il2fb/config/difficulty/constants.py
il2fb/config/difficulty/exceptions.py
il2fb/config/difficulty/validators.py
il2fb/config/difficulty/locale/en/LC_MESSAGES/il2fb-difficulty.mo
il2fb/config/difficulty/locale/en/LC_MESSAGES/il2fb-difficulty.po
il2fb/config/difficulty/locale/ru/LC_MESSAGES/il2fb-difficulty.mo
il2fb/config/difficulty/locale/ru/LC_MESSAGES/il2fb-difficulty.po
il2fb/config/difficulty/utils/__init__.py
il2fb/config/difficulty/utils/bitwise.py
il2fb/config/difficulty/utils/transforms.py
il2fb_difficulty.egg-info/PKG-INFO
il2fb_difficulty.egg-info/SOURCES.txt
il2fb_difficulty.egg-info/dependency_links.txt
il2fb_difficulty.egg-info/namespace_packages.txt
il2fb_difficulty.egg-info/requires.txt
il2fb_difficulty.egg-info/top_level.txt
requirements/dist.txt