Metadata-Version: 1.1
Name: il2fb-difficulty
Version: 1.3.0
Summary: Parser and emitter of difficulty settings for IL-2 FB
Home-page: https://github.com/IL2HorusTeam/il2fb-difficulty/
Author: Alexander Oblovatniy, Alexander Kamyhin
Author-email: oblovatniy@gmail.com, kamyhin@gmail.com
License: LGPLv3
Keywords: il2,il-2,fb,forgotten battles,difficulty,parser,emitter,config,difficulty
Platform: any
Classifier: Development Status :: 5 - Production/Stable
Classifier: Intended Audience :: Developers
Classifier: License :: OSI Approved :: GNU Lesser General Public License v3 (LGPLv3)
Classifier: Natural Language :: English
Classifier: Operating System :: OS Independent
Classifier: Programming Language :: Python :: 2.7
Classifier: Programming Language :: Python :: 3.4
Classifier: Programming Language :: Python :: 3.5
Classifier: Programming Language :: Python :: 3.6
Classifier: Topic :: Software Development :: Libraries
